LICENSE.txt
README.rst
setup.cfg
setup.py
statu/__init__.py
statu.egg-info/PKG-INFO
statu.egg-info/SOURCES.txt
statu.egg-info/dependency_links.txt
statu.egg-info/not-zip-safe
statu.egg-info/requires.txt
statu.egg-info/top_level.txt
statu/models/__init__.py
statu/orm/__init__.py
statu/orm/base.py
statu/orm/sqlalchemy.py